discord_data/__init__.py
discord_data/__main__.py
discord_data/common.py
discord_data/error.py
discord_data/merge.py
discord_data/model.py
discord_data/parse.py
discord_data/py.typed
discord_data-0.2.3.dist-info/licenses/LICENSE
discord_data-0.2.3.dist-info/METADATA
discord_data-0.2.3.dist-info/WHEEL
discord_data-0.2.3.dist-info/entry_points.txt
discord_data-0.2.3.dist-info/top_level.txt
discord_data-0.2.3.dist-info/RECORD
