Metadata-Version: 2.4
Name: discord_data
Version: 0.2.3
Summary: Library to parse the Discord GDPR export
Author: purarue
License-Expression: MIT
Project-URL: Homepage, https://github.com/purarue/discord_data
Keywords: discord,data
Classifier: Programming Language :: Python :: 3
Classifier: Programming Language :: Python :: 3 :: Only
Classifier: Programming Language :: Python :: 3.9
Classifier: Programming Language :: Python :: 3.10
Classifier: Programming Language :: Python :: 3.11
Classifier: Programming Language :: Python :: 3.12
Classifier: Programming Language :: Python :: 3.13
Requires-Python: >=3.9
License-File: LICENSE
Requires-Dist: click>=8.1.0
Requires-Dist: simplejson
Dynamic: license-file
